codenerix_email/__init__.py
codenerix_email/admin.py
codenerix_email/apps.py
codenerix_email/forms.py
codenerix_email/models.py
codenerix_email/urls.py
codenerix_email/urls_frontend.py
codenerix_email/views.py
codenerix_email/management/__init__.py
codenerix_email/management/__pycache__/__init__.cpython-310.pyc
codenerix_email/management/__pycache__/__init__.cpython-311.pyc
codenerix_email/management/__pycache__/__init__.cpython-35.pyc
codenerix_email/management/__pycache__/__init__.cpython-39.pyc
codenerix_email/management/commands/__init__.py
codenerix_email/management/commands/recv_emails.py
codenerix_email/management/commands/send_emails.py
codenerix_email/management/commands/test_email.py
codenerix_email/management/commands/__pycache__/__init__.cpython-310.pyc
codenerix_email/management/commands/__pycache__/__init__.cpython-311.pyc
codenerix_email/management/commands/__pycache__/recv_emails.cpython-310.pyc
codenerix_email/management/commands/__pycache__/send_emails.cpython-311.pyc
codenerix_email/management/commands/__pycache__/test_email.cpython-310.pyc
codenerix_email/migrations/0001_initial.py
codenerix_email/migrations/0002_auto_20170502_1043.py
codenerix_email/migrations/0003_auto_20170921_1206.py
codenerix_email/migrations/0004_auto_20171108_1628.py
codenerix_email/migrations/0005_emailmessage_retries.py
codenerix_email/migrations/0006_emailmessage_error.py
codenerix_email/migrations/0007_emailmessage_next_retry.py
codenerix_email/migrations/0008_auto_20171201_0928.py
codenerix_email/migrations/0009_emailmessage_opened_emailmessage_uuid.py
codenerix_email/migrations/0010_emailmessage_content_subtype_and_more.py
codenerix_email/migrations/0011_alter_emailmessage_content_subtype_and_more.py
codenerix_email/migrations/0012_emailmessage_unsubscribe_url.py
codenerix_email/migrations/0013_emailmessage_headers.py
codenerix_email/migrations/0014_emailreceived.py
codenerix_email/migrations/__init__.py
django_codenerix_email-4.0.30.dist-info/LICENSE
django_codenerix_email-4.0.30.dist-info/METADATA
django_codenerix_email-4.0.30.dist-info/WHEEL
django_codenerix_email-4.0.30.dist-info/top_level.txt
django_codenerix_email-4.0.30.dist-info/RECORD
