Metadata-Version: 2.1
Name: django-codenerix-email
Version: 4.0.30
Summary: Codenerix Email is a module that enables CODENERIX to set send emails in a general manner.
Home-page: https://github.com/codenerix/django-codenerix-email
Author: Juan Miguel Taboada Godoy <juanmi@juanmitaboada.com>, Juan Soler Ruiz <soleronline@gmail.com>
License: Apache License Version 2.0
Keywords: django,codenerix,management,erp,crm,send email
Platform: OS Independent
Classifier: Environment :: Web Environment
Classifier: Framework :: Django
Classifier: Framework :: Django :: 1.8
Classifier: Framework :: Django :: 1.9
Classifier: Framework :: Django :: 1.10
Classifier: Intended Audience :: Developers
Classifier: License :: Other/Proprietary License
Classifier: Operating System :: OS Independent
Classifier: Programming Language :: Python
Classifier: Programming Language :: Python :: 2
Classifier: Programming Language :: Python :: 2.7
Classifier: Programming Language :: Python :: 3
Classifier: Programming Language :: Python :: 3.4
Classifier: Programming Language :: Python :: 3.5
Classifier: Topic :: Internet :: WWW/HTTP
Classifier: Topic :: Internet :: WWW/HTTP :: Dynamic Content
License-File: LICENSE
Requires-Dist: IMAPClient (>=3.0.1)
Requires-Dist: django-codenerix (>=5.0.40)
Requires-Dist: django-codenerix-extensions (>=4.0.4)
